cect/Analysis.py
cect/BrittinDataReader.py
cect/CellAnalysis.py
cect/CellInfo.py
cect/Cells.py
cect/Comparison.py
cect/ConnectomeDataset.py
cect/ConnectomeReader.py
cect/ConnectomeView.py
cect/Cook2019DataReader.py
cect/Cook2019HermReader.py
cect/Cook2019MaleReader.py
cect/Cook2020DataReader.py
cect/GleesonModelReader.py
cect/NeuroMLDataReader.py
cect/OlivaresModelReader.py
cect/OpenWormUnifiedReader.py
cect/RipollSanchezDataReader.py
cect/RipollSanchezLongRangeReader.py
cect/RipollSanchezMidRangeReader.py
cect/RipollSanchezShortRangeReader.py
cect/SpreadsheetDataReader.py
cect/TestDataReader.py
cect/UpdatedSpreadsheetDataReader.py
cect/UpdatedSpreadsheetDataReader2.py
cect/VarshneyDataReader.py
cect/WhiteDataReader.py
cect/White_A.py
cect/White_L4.py
cect/White_whole.py
cect/WitvlietDataReader.py
cect/WitvlietDataReader1.py
cect/WitvlietDataReader2.py
cect/WitvlietDataReader3.py
cect/WitvlietDataReader4.py
cect/WitvlietDataReader5.py
cect/WitvlietDataReader6.py
cect/WitvlietDataReader7.py
cect/WitvlietDataReader8.py
cect/WormAtlasInfo.py
cect/WormNeuroAtlasExtSynReader.py
cect/WormNeuroAtlasFuncReader.py
cect/WormNeuroAtlasMAReader.py
cect/WormNeuroAtlasPepReader.py
cect/WormNeuroAtlasReader.py
cect/Yim2024DataReader.py
cect/__init__.py
cect/cache/BrittinDataReader.json
cect/cache/Cook2019HermReader.json
cect/cache/Cook2019MaleReader.json
cect/cache/Cook2020DataReader.json
cect/cache/RipollSanchezLongRangeReader.json
cect/cache/RipollSanchezMidRangeReader.json
cect/cache/RipollSanchezShortRangeReader.json
cect/cache/SpreadsheetDataReader.json
cect/cache/TestDataReader.json
cect/cache/UpdatedSpreadsheetDataReader.json
cect/cache/UpdatedSpreadsheetDataReader2.json
cect/cache/VarshneyDataReader.json
cect/cache/White_A.json
cect/cache/White_L4.json
cect/cache/White_whole.json
cect/cache/WitvlietDataReader1.json
cect/cache/WitvlietDataReader2.json
cect/cache/WitvlietDataReader3.json
cect/cache/WitvlietDataReader4.json
cect/cache/WitvlietDataReader5.json
cect-0.2.5.dist-info/METADATA
cect-0.2.5.dist-info/WHEEL
cect-0.2.5.dist-info/top_level.txt
cect-0.2.5.dist-info/RECORD
