Metadata-Version: 2.1
Name: cect
Version: 0.2.5
Summary: C. elegans Connectome Toolbox
Home-page: https://github.com/openworm/ConnectomeToolbox
Author: OpenWorm contributors
Author-email: p.gleeson@gmail.com
Maintainer: Padraig Gleeson
Maintainer-email: p.gleeson@gmail.com
License: LGPLv3
Classifier: Intended Audience :: Science/Research
Classifier: License :: OSI Approved :: GNU Lesser General Public License v3 (LGPLv3)
Classifier: Natural Language :: English
Classifier: Operating System :: OS Independent
Classifier: Topic :: Scientific/Engineering
Classifier: Intended Audience :: Science/Research
Classifier: Programming Language :: Python
Classifier: Programming Language :: Python :: 3
Classifier: Programming Language :: Python :: 3 :: Only
Classifier: Programming Language :: Python :: 3.8
Classifier: Programming Language :: Python :: 3.9
Classifier: Programming Language :: Python :: 3.10
Classifier: Programming Language :: Python :: 3.11
Classifier: Programming Language :: Python :: 3.12
Classifier: Topic :: Scientific/Engineering
Classifier: Topic :: Software Development
Classifier: Typing :: Typed
Requires-Python: >=3.7
Requires-Dist: numpy
Requires-Dist: xlrd
Requires-Dist: openpyxl
Requires-Dist: wormneuroatlas
Requires-Dist: networkx
Requires-Dist: hiveplotlib
Requires-Dist: webcolors
Requires-Dist: pyneuroml
Provides-Extra: all
Requires-Dist: cect[test] ; extra == 'all'
Requires-Dist: cect[docs] ; extra == 'all'
Requires-Dist: cect[dev] ; extra == 'all'
Provides-Extra: dev
Requires-Dist: flake8 ; extra == 'dev'
Requires-Dist: cect[test] ; extra == 'dev'
Requires-Dist: pre-commit ; extra == 'dev'
Requires-Dist: tabulate ; extra == 'dev'
Requires-Dist: ruff ; extra == 'dev'
Provides-Extra: docs
Requires-Dist: pandas ; extra == 'docs'
Requires-Dist: tabulate ; extra == 'docs'
Requires-Dist: mkdocs ; extra == 'docs'
Requires-Dist: mkdocs-material ; extra == 'docs'
Requires-Dist: mkdocs-plotly-plugin ; extra == 'docs'
Requires-Dist: mkdocs-charts-plugin ; extra == 'docs'
Requires-Dist: mkdocs-autoapi[python] (>=0.3.1) ; extra == 'docs'
Requires-Dist: plotly (<6.0.0) ; extra == 'docs'
Requires-Dist: kaleido (<0.4) ; extra == 'docs'
Provides-Extra: test
Requires-Dist: pytest ; extra == 'test'
Requires-Dist: pytest-benchmark ; extra == 'test'
Requires-Dist: pytest-mock ; extra == 'test'
Requires-Dist: typing-extensions ; (python_version < "3.8") and extra == 'test'
